[
    {
        "selector": "node",
        "style": {
            "content": "data(label)",
			"text-valign": "center",
			"text-halign": "center",
            "width": "60px",
            "height": "60px",
            "color": "orange",
            "text-background-color": "blue",
            "shape": "ellipse"
        }
    }, {
        "selector": "edge",
        "style": {
            "label": "data(label)",
            "text-background-opacity": 0.3,
            "width": "6px",
            "target-arrow-shape": "triangle"
        }
    }, {
      "selector": "node:selected",
      "style": {
        "background-color": "orange",
        "line-color": "black",
        "target-arrow-color": "black",
        "source-arrow-color": "black"
      }
	}
]
